mkdocs_tacc/__init.py__
mkdocs_tacc/tacc_readthedocs/README.md
mkdocs_tacc/tacc_readthedocs/__init__.py
mkdocs_tacc/tacc_readthedocs/css/tacc-theme/bootstrap.css
mkdocs_tacc/tacc_readthedocs/css/tacc-theme/core-docs.css
mkdocs_tacc/tacc_readthedocs/css/tacc-theme/core-styles.base.css
mkdocs_tacc/tacc_readthedocs/css/tacc-theme/core-styles.docs.css
mkdocs_tacc/tacc_readthedocs/css/tacc-theme/highlight-js.css
mkdocs_tacc/tacc_readthedocs/css/tacc-theme/mkdocs.css
mkdocs_tacc/tacc_readthedocs/css/tacc-theme/pymdownx.css
mkdocs_tacc/tacc_readthedocs/css/tacc-theme/python-markdown.css
mkdocs_tacc/tacc_readthedocs/css/tacc-theme/readthedocs-reskin.css
mkdocs_tacc/tacc_readthedocs/css/tacc-theme/readthedocs-revert.css
mkdocs_tacc/tacc_readthedocs/css/tacc-theme.css
mkdocs_tacc/tacc_readthedocs/footer.html
mkdocs_tacc/tacc_readthedocs/img/favicon.ico
mkdocs_tacc/tacc_readthedocs/img/logo-tacc.svg
mkdocs_tacc/tacc_readthedocs/img/logo.svg
mkdocs_tacc/tacc_readthedocs/js/tacc-theme/addIconToExternalLinks.js
mkdocs_tacc/tacc_readthedocs/js/tacc-theme/addPageNameToRoot.js
mkdocs_tacc/tacc_readthedocs/js/tacc-theme/autoScrollNavOnPageReload.js
mkdocs_tacc/tacc_readthedocs/js/tacc-theme/redirectNavLinks.js
mkdocs_tacc/tacc_readthedocs/js/tacc-theme/removeSectionClass.js
mkdocs_tacc/tacc_readthedocs/js/tacc-theme/setTargetForExternalLinks.module.js
mkdocs_tacc/tacc_readthedocs/js/tacc-theme/swapImgSvgWithRawSvg.module.js
mkdocs_tacc/tacc_readthedocs/js/tacc-theme.module.js
mkdocs_tacc/tacc_readthedocs/locales/en/LC_MESSAGES/messages.mo
mkdocs_tacc/tacc_readthedocs/locales/en/LC_MESSAGES/messages.po
mkdocs_tacc/tacc_readthedocs/main.html
mkdocs_tacc/tacc_readthedocs/mkdocs_theme.yml
mkdocs_tacc/tacc_readthedocs/nav.html
mkdocs_tacc/tacc_readthedocs/searchbox.html
mkdocs_tacc-1.0.2.dist-info/METADATA
mkdocs_tacc-1.0.2.dist-info/WHEEL
mkdocs_tacc-1.0.2.dist-info/entry_points.txt
mkdocs_tacc-1.0.2.dist-info/licenses/LICENSE
mkdocs_tacc-1.0.2.dist-info/RECORD
