Metadata-Version: 2.4
Name: mkdocs-tacc
Version: 1.0.2
Summary: TACC-specific MkDocs theme
License: MIT License
License-File: LICENSE
Author: TACC COA CMD
Author-email: coa-cmd@tacc.utexas.edu
Maintainer: TACC COA CMD
Maintainer-email: coa-cmd@tacc.utexas.edu
Requires-Python: >=3.10,<3.13
Classifier: Development Status :: 3 - Alpha
Classifier: Environment :: Web Environment
Classifier: Framework :: MkDocs
Classifier: Intended Audience :: Information Technology
Classifier: License :: OSI Approved :: BSD License
Classifier: License :: Other/Proprietary License
Classifier: Operating System :: OS Independent
Classifier: Programming Language :: Python :: 3
Classifier: Programming Language :: Python :: 3.10
Classifier: Programming Language :: Python :: 3.11
Classifier: Programming Language :: Python :: 3.12
Classifier: Topic :: Documentation
Provides-Extra: all
Provides-Extra: i18n
Provides-Extra: pymdown-extensions
Requires-Dist: mkdocs (==1.4.3)
Requires-Dist: mkdocs[i18n] (==1.4.3) ; extra == "all"
Requires-Dist: mkdocs[i18n] (==1.4.3) ; extra == "i18n"
Requires-Dist: pymdown-extensions (>=10.4.0) ; extra == "all"
Requires-Dist: pymdown-extensions (>=10.4.0) ; extra == "pymdown-extensions"
Project-URL: Documentation, https://tacc.github.io/mkdocs-tacc
Project-URL: Homepage, https://tacc.github.io/mkdocs-tacc
Project-URL: changelog, https://github.com/TACC/mkdocs-tacc/releases
Project-URL: github, https://github.com/TACC/mkdocs-tacc
Project-URL: issues, https://github.com/TACC/mkdocs-tacc/issues
